FMEA.py
FMEA-0.0.1.dist-info/METADATA
FMEA-0.0.1.dist-info/WHEEL
FMEA-0.0.1.dist-info/license
FMEA-0.0.1.dist-info/top_level.txt
FMEA-0.0.1.dist-info/RECORD
