Metadata-Version: 2.1
Name: FMEA
Version: 0.0.1
Summary: A flexible Mutable Symmetric Encryption algorithm
Home-page: https://github.com/ApratimR/FMEA
Author: Apratim Ray
Author-email: apratimr55@gmail.com
License: UNKNOWN
Platform: UNKNOWN
Classifier: Programming Language :: Python :: 3
Classifier: License :: OSI Approved :: GNU General Public License v3 (GPLv3)
Classifier: Operating System :: OS Independent
Requires-Python: >=3.6
Requires-Dist: numpy
Requires-Dist: FNNH
